{
    "version": "https://jsonfeed.org/version/1",
    "title": "WKS Dedetizadora",
    "description": "",
    "home_page_url": "https://wksdedetizadora.github.io",
    "feed_url": "https://wksdedetizadora.github.io/feed.json",
    "user_comment": "",
    "icon": "https://wksdedetizadora.github.io/media/website/wkslogo-2.jpeg",
    "author": {
        "name": "Israel Cerqueira"
    },
    "items": [
        {
            "id": "https://wksdedetizadora.github.io/obrigado/",
            "url": "https://wksdedetizadora.github.io/obrigado/",
            "title": "Obrigado",
            "summary": "Obrigado!! Muito obrigado por entrar em contato conosco! Nós entraremos em contato&hellip;",
            "content_html": "<h2>Obrigado!!</h2>\n<p> </p>\n<p>Muito obrigado por entrar em contato conosco!</p>\n<p>Nós entraremos em contato com você o mais breve possível.</p>",
            "author": {
                "name": "Israel Cerqueira"
            },
            "tags": [
            ],
            "date_published": "2020-04-26T19:17:17-03:00",
            "date_modified": "2020-12-15T21:10:18-03:00"
        },
        {
            "id": "https://wksdedetizadora.github.io/fale-conosco/",
            "url": "https://wksdedetizadora.github.io/fale-conosco/",
            "title": "Fale conosco",
            "summary": "Olá, vamos conversar?Fale conosco a qualquer momento. O que você está pensando agora? Deixe-nos&hellip;",
            "content_html": "<h2>Olá, vamos conversar?</h2>\n<p>Fale conosco a qualquer momento. O que você está pensando agora? Deixe-nos uma mensagem:</p>\n<p> </p>\n<form action=\" https://formsubmit.co/israel.cerqueira@gmail.com\" method=\"POST\"><input name=\"name\" type=\"text\" placeholder=\"Seu nome\"><br><input name=\"email\" type=\"email\" placeholder=\"E-mail\"><br><input name=\"tel\" type=\"text\" placeholder=\"Telefone(whatsapp)\"><br><textarea name=\"mensagem\" placeholder=\"Mensagem\"></textarea><br><input name=\"_replyto\" type=\"hidden\"> <input name=\"_next\" type=\"hidden\" value=\"https://wksdedetizadora.com/obrigado\"> <input name=\"_subject\" type=\"hidden\" value=\"WKSDedetizadora Contato\"><br><input name=\"_captcha\" type=\"hidden\" value=\"false\"><input name=\"_webhook\" type=\"hidden\" value=\"https://69559f204b1519c710c84e3de6b20928.m.pipedream.net\"> <button type=\"submit\">Enviar</button></form>\n<p> </p>\n<p>Se preferir, este é o nosso telefone para contato:</p>\n<h3>(71) 99238.4651</h3>",
            "author": {
                "name": "Israel Cerqueira"
            },
            "tags": [
            ],
            "date_published": "2020-04-25T01:23:56-03:00",
            "date_modified": "2020-12-15T21:10:09-03:00"
        },
        {
            "id": "https://wksdedetizadora.github.io/poda-de-arvores/",
            "url": "https://wksdedetizadora.github.io/poda-de-arvores/",
            "title": "Desinsetização",
            "summary": "DesinsetizaçãoSomos especializados em serviços de desinsetização para controle de insetos rasteiros como&hellip;",
            "content_html": "<h2>Desinsetização</h2>\n<p>Somos especializados em serviços de desinsetização para controle de insetos rasteiros como baratas, formigas, aranhas, traças, pulgas, carrapatos, percevejos, escorpiões, moscas e mosquitos em residências e empresas, sempre focados na qualidade, satisfação e segurança.</p>\n<p>Veja um pouco do nosso trabalho (clique para ampliar):</p>\n<div class=\"gallery-wrapper\"><div class=\"gallery\"  data-is-empty=\"false\" data-columns=\"4\">\n<figure class=\"gallery__item\"><a href=\"https://wksdedetizadora.github.io/media/posts/5/gallery/images-1.jpeg\" data-size=\"678x452\"><img loading=\"lazy\" src=\"https://wksdedetizadora.github.io/media/posts/5/gallery/images-1-thumbnail.jpeg\" alt=\"\" width=\"678\" height=\"452\"></a></figure>\n<figure class=\"gallery__item\"><a href=\"https://wksdedetizadora.github.io/media/posts/5/gallery/images-2-1.jpeg\" data-size=\"600x450\"><img loading=\"lazy\" src=\"https://wksdedetizadora.github.io/media/posts/5/gallery/images-2-1-thumbnail.jpeg\" alt=\"\" width=\"600\" height=\"450\"></a></figure>\n</div></div>",
            "image": "https://wksdedetizadora.github.io/media/posts/5/9c2acd84-c0f5-4529-9e42-9a36d79a42c9.jpg",
            "author": {
                "name": "Israel Cerqueira"
            },
            "tags": [
                   "servicos"
            ],
            "date_published": "2020-04-24T00:46:39-03:00",
            "date_modified": "2020-12-15T20:49:48-03:00"
        },
        {
            "id": "https://wksdedetizadora.github.io/paisagismo/",
            "url": "https://wksdedetizadora.github.io/paisagismo/",
            "title": "Desratização",
            "summary": "DesratizaçãoRealizamos o controle de ratos em residências e empresas, agregando técnica com&hellip;",
            "content_html": "<h2>Desratização</h2>\n<p>Realizamos o controle de ratos em residências e empresas, agregando técnica com a necessidade dos nossos clientes, sendo ele <strong>CONDOMÍNIO</strong>, <strong>EMPRESA</strong> ou <strong>RESIDÊNCIA.</strong></p>\n<p>Executamos o extermínio, prevenção e monitoramento <strong>sem a necessidade de desocupar o ambiente.</strong><br><br>Oferecemos alta proteção preventiva com risco zero.</p>\n<p>Veja um pouco do nosso trabalho (clique para ampliar):</p>\n<div class=\"gallery-wrapper\"><div class=\"gallery\"  data-is-empty=\"false\" data-columns=\"4\">\n<figure class=\"gallery__item\"><a href=\"https://wksdedetizadora.github.io/media/posts/4/gallery/images-3.jpeg\" data-size=\"771x381\"><img loading=\"lazy\" src=\"https://wksdedetizadora.github.io/media/posts/4/gallery/images-3-thumbnail.jpeg\" alt=\"\" width=\"768\" height=\"380\"></a></figure>\n<figure class=\"gallery__item\"><a href=\"https://wksdedetizadora.github.io/media/posts/4/gallery/desratizacao-sp.jpg\" data-size=\"232x217\"><img loading=\"lazy\" src=\"https://wksdedetizadora.github.io/media/posts/4/gallery/desratizacao-sp-thumbnail.jpg\" alt=\"\" width=\"232\" height=\"217\"></a></figure>\n</div></div>",
            "image": "https://wksdedetizadora.github.io/media/posts/4/Rio-3.jpg",
            "author": {
                "name": "Israel Cerqueira"
            },
            "tags": [
                   "servicos"
            ],
            "date_published": "2020-04-24T00:40:34-03:00",
            "date_modified": "2020-12-15T20:56:18-03:00"
        },
        {
            "id": "https://wksdedetizadora.github.io/manutencao-jardim/",
            "url": "https://wksdedetizadora.github.io/manutencao-jardim/",
            "title": "Descupinização",
            "summary": "DescupinizaçãoA descupinização é um trabalho essencial para manter o controle das principais&hellip;",
            "content_html": "<h2>Descupinização</h2>\n<p>A descupinização é um trabalho essencial para manter o controle das principais espécies de cupins em residências e empresas.<br><br></p>\n<p>Veja um pouco do nosso trabalho (clique para ampliar):</p>\n<div class=\"gallery-wrapper\"><div class=\"gallery\"  data-is-empty=\"false\" data-columns=\"5\">\n<figure class=\"gallery__item\"><a href=\"https://wksdedetizadora.github.io/media/posts/3/gallery/images.jpeg\" data-size=\"720x426\"><img loading=\"lazy\" src=\"https://wksdedetizadora.github.io/media/posts/3/gallery/images-thumbnail.jpeg\" alt=\"\" width=\"720\" height=\"426\"></a></figure>\n<figure class=\"gallery__item\"><a href=\"https://wksdedetizadora.github.io/media/posts/3/gallery/Descupinizacao-de-moveis-especies.jpg\" data-size=\"626x417\"><img loading=\"lazy\" src=\"https://wksdedetizadora.github.io/media/posts/3/gallery/Descupinizacao-de-moveis-especies-thumbnail.jpg\" alt=\"\" width=\"626\" height=\"417\"></a></figure>\n</div></div>\n<p>Nossos serviços de Descupinização são realizadas por profissionais que estão sempre em treinamento e empenhados no bem estar dos nossos clientes.</p>\n<p>Realizamos o serviço de Descupinização em <strong>CONDOMÍNIOS</strong>, <strong>EMPRESAS</strong> e <strong>RESIDÊNCIAS</strong>.</p>",
            "image": "https://wksdedetizadora.github.io/media/posts/3/20180607_090001.jpg",
            "author": {
                "name": "Israel Cerqueira"
            },
            "tags": [
                   "servicos"
            ],
            "date_published": "2020-04-24T00:29:25-03:00",
            "date_modified": "2020-12-15T20:59:44-03:00"
        },
        {
            "id": "https://wksdedetizadora.github.io/implantacao-gramado/",
            "url": "https://wksdedetizadora.github.io/implantacao-gramado/",
            "title": "Sanitização de ambiente",
            "summary": "Sanitização de ambienteSanitização de ambiente para o combate a bactérias, ácaros, fungos&hellip;",
            "content_html": "<h2>Sanitização de ambiente</h2>\n<p>Sanitização de ambiente para o combate a bactérias, ácaros, fungos e vírus como o covid-19.</p>\n<p>Veja um pouco do nosso trabalho de implantação de gramados (clique para ampliar):</p>\n<div class=\"gallery-wrapper\"><div class=\"gallery\"  data-is-empty=\"false\" data-columns=\"4\">\n<figure class=\"gallery__item\"><a href=\"https://wksdedetizadora.github.io/media/posts/2/gallery/images-4.jpeg\" data-size=\"579x316\"><img loading=\"lazy\" src=\"https://wksdedetizadora.github.io/media/posts/2/gallery/images-4-thumbnail.jpeg\" alt=\"\" width=\"579\" height=\"316\"></a></figure>\n<figure class=\"gallery__item\"><a href=\"https://wksdedetizadora.github.io/media/posts/2/gallery/c1667055b4667ffdd5b09e569b37e5d5_XL.jpg\" data-size=\"725x375\"><img loading=\"lazy\" src=\"https://wksdedetizadora.github.io/media/posts/2/gallery/c1667055b4667ffdd5b09e569b37e5d5_XL-thumbnail.jpg\" alt=\"\" width=\"725\" height=\"375\"></a></figure>\n</div></div>\n<p>Na sanitização de ambientes trabalhamos com todo cuidado para garantir que o ambiente fique livre de contaminação.<br><br></p>",
            "image": "https://wksdedetizadora.github.io/media/posts/2/Impla-7.jpg",
            "author": {
                "name": "Israel Cerqueira"
            },
            "tags": [
                   "servicos"
            ],
            "date_published": "2020-04-21T03:15:55-03:00",
            "date_modified": "2020-12-15T21:06:05-03:00"
        },
        {
            "id": "https://wksdedetizadora.github.io/nossas-especialidades/",
            "url": "https://wksdedetizadora.github.io/nossas-especialidades/",
            "title": "Nossas especialidades",
            "summary": "Nossas EspecialidadesSomos especializados em serviços de: Buscamos sempre unir a técnica com a&hellip;",
            "content_html": "<h2>Nossas Especialidades</h2>\n<p>Somos especializados em serviços de:</p>\n<ul>\n<li>Desinsetização</li>\n<li>Desratização</li>\n<li>Descupinização</li>\n<li>Sanitização de ambiente</li>\n</ul>\n<p>Buscamos sempre unir a técnica com a necessidade dos nossos clientes, sendo ele CONDOMÍNIO, EMPRESA ou RESIDÊNCIA.</p>",
            "image": "https://wksdedetizadora.github.io/media/posts/1/Post1.jpg",
            "author": {
                "name": "Israel Cerqueira"
            },
            "tags": [
                   "servicos"
            ],
            "date_published": "2020-04-20T20:00:51-03:00",
            "date_modified": "2020-12-15T20:50:09-03:00"
        }
    ]
}
